asyncyt/__init__.py
asyncyt/_version.py
asyncyt/basemodels.py
asyncyt/binaries.py
asyncyt/core.py
asyncyt/enums.py
asyncyt/exceptions.py
asyncyt/utils.py
asyncyt-1.5.0.dist-info/METADATA
asyncyt-1.5.0.dist-info/WHEEL
asyncyt-1.5.0.dist-info/licenses/LICENSE
asyncyt-1.5.0.dist-info/RECORD
