Metadata-Version: 2.4
Name: asyncyt
Version: 1.5.0
Summary: A fully asynchronous media downloader for 1000+ websites, powered by yt-dlp and FFmpeg
Project-URL: Homepage, https://github.com/mahirox36/AsyncYT
Project-URL: Documentation, https://asyncyt.mahirou.online/
Author-email: MahiroX36 <mahiroc36@gmail.com>
License: MIT
License-File: LICENSE
Keywords: async,downloader,ffmpeg,python,youtube,yt-dlp
Requires-Python: >=3.11
Requires-Dist: aiofiles
Requires-Dist: aiohttp
Requires-Dist: pydantic>=2.0
